dearwatson-1.0.1.dist-info/licenses/LICENSE
watson/__init__.py
watson/constants.py
watson/neighbours.py
watson/report.py
watson/watson.py
watson/data_validation_report/DvrPreparer.py
watson/data_validation_report/__init__.py
watson/resources/images/sherlock3.png
watson/resources/images/watson.png
watson/tests/__init__.py
watson/tests/test_watson.py
watson/tpfplotterSub/__init__.py
watson/tpfplotterSub/tpfplotter.py
watson/tpfplotterSub/tpfplotter_py2.py
dearwatson-1.0.1.dist-info/METADATA
dearwatson-1.0.1.dist-info/WHEEL
dearwatson-1.0.1.dist-info/top_level.txt
dearwatson-1.0.1.dist-info/RECORD
