Metadata-Version: 2.4
Name: dearwatson
Version: 1.0.1
Summary: Visual Vetting and Analysis of Transits from Space ObservatioNs
Home-page: https://github.com/PlanetHunters/watson
Author: M. Dévora-Pajares
Author-email: mdevorapajares@protonmail.com
Classifier: Programming Language :: Python :: 3
Classifier: License :: OSI Approved :: MIT License
Classifier: Operating System :: OS Independent
Requires-Python: >=3.11
License-File: LICENSE
Requires-Dist: arviz==0.21.0
Requires-Dist: bokeh==3.7.3
Requires-Dist: configparser==5.0.1
Requires-Dist: extension-helpers==0.1
Requires-Dist: exoml==1.3.2
Requires-Dist: imageio==2.9.0
Requires-Dist: openai==1.30.1
Requires-Dist: pdf2image==1.16.2
Requires-Dist: pyparsing==2.4.7
Requires-Dist: pyyaml==6.0.1
Requires-Dist: pillow==11.2.1
Requires-Dist: pytransit==2.6.14
Requires-Dist: reportlab==4.4.0
Requires-Dist: setuptools>=41.0.0
Requires-Dist: triceratops==1.0.19
Dynamic: author
Dynamic: author-email
Dynamic: classifier
Dynamic: description
Dynamic: description-content-type
Dynamic: home-page
Dynamic: license-file
Dynamic: requires-dist
Dynamic: requires-python
Dynamic: summary
